{"format":2,"version":"7.2.4","globals":"3fb63cd10552aea2f3c024d694bf1e40","files":{"main_py":{"hash":"a9295e45aa87b78a33436488161f11d2","index":{"nums":[0,1,62,0,4,0,0,0],"html_filename":"main_py.html","relative_filename":"main.py"}},"models_py":{"hash":"4d78175eab4fc3b5a4fbe9fdfaa457cc","index":{"nums":[0,1,23,0,2,0,0,0],"html_filename":"models_py.html","relative_filename":"models.py"}},"schemas_py":{"hash":"a5f17e2c9639d512755def90f8f5437b","index":{"nums":[0,1,17,0,0,0,0,0],"html_filename":"schemas_py.html","relative_filename":"schemas.py"}},"settings_py":{"hash":"3da1589b88444802ad44151b1beb15ba","index":{"nums":[0,1,16,0,0,0,0,0],"html_filename":"settings_py.html","relative_filename":"settings.py"}},"d_a44f0ac069e85531_test_main_py":{"hash":"81443fc370994139414f520f4622301f","index":{"nums":[0,1,74,0,0,0,0,0],"html_filename":"d_a44f0ac069e85531_test_main_py.html","relative_filename":"tests/test_main.py"}},"utils_py":{"hash":"ada6550cc2f8881c98b9a56b93e5c475","index":{"nums":[0,1,51,0,19,0,0,0],"html_filename":"utils_py.html","relative_filename":"utils.py"}}}}